[
    {
        "Hammer Date": "1997-05-22",
        "Next Day Percent Change": "6.67 %"
    },
    {
        "Hammer Date": "1997-08-18",
        "Next Day Percent Change": "3.48 %"
    },
    {
        "Hammer Date": "1998-03-26",
        "Next Day Percent Change": "0.89 %"
    },
    {
        "Hammer Date": "1998-12-07",
        "Next Day Percent Change": "7.61 %"
    },
    {
        "Hammer Date": "2001-02-14",
        "Next Day Percent Change": "7.41 %"
    },
    {
        "Hammer Date": "2002-01-17",
        "Next Day Percent Change": "5.83 %"
    },
    {
        "Hammer Date": "2002-02-20",
        "Next Day Percent Change": "2.71 %"
    },
    {
        "Hammer Date": "2002-12-10",
        "Next Day Percent Change": "2.12 %"
    },
    {
        "Hammer Date": "2003-05-01",
        "Next Day Percent Change": "2.79 %"
    },
    {
        "Hammer Date": "2004-09-09",
        "Next Day Percent Change": "1.15 %"
    },
    {
        "Hammer Date": "2005-02-11",
        "Next Day Percent Change": "1.07 %"
    },
    {
        "Hammer Date": "2005-08-19",
        "Next Day Percent Change": "0.37 %"
    },
    {
        "Hammer Date": "2006-11-03",
        "Next Day Percent Change": "1.51 %"
    },
    {
        "Hammer Date": "2007-08-01",
        "Next Day Percent Change": "2.38 %"
    },
    {
        "Hammer Date": "2007-08-16",
        "Next Day Percent Change": "0.71 %"
    },
    {
        "Hammer Date": "2008-01-23",
        "Next Day Percent Change": "4.21 %"
    },
    {
        "Hammer Date": "2009-12-18",
        "Next Day Percent Change": "1.77 %"
    },
    {
        "Hammer Date": "2010-02-02",
        "Next Day Percent Change": "1.69 %"
    },
    {
        "Hammer Date": "2010-03-15",
        "Next Day Percent Change": "0.42 %"
    },
    {
        "Hammer Date": "2011-10-04",
        "Next Day Percent Change": "3.28 %"
    },
    {
        "Hammer Date": "2012-04-23",
        "Next Day Percent Change": "0.87 %"
    },
    {
        "Hammer Date": "2012-07-12",
        "Next Day Percent Change": "1.28 %"
    },
    {
        "Hammer Date": "2012-07-17",
        "Next Day Percent Change": "0.61 %"
    },
    {
        "Hammer Date": "2013-02-26",
        "Next Day Percent Change": "1.48 %"
    },
    {
        "Hammer Date": "2013-11-04",
        "Next Day Percent Change": "0.59 %"
    },
    {
        "Hammer Date": "2014-01-06",
        "Next Day Percent Change": "0.76 %"
    },
    {
        "Hammer Date": "2014-05-09",
        "Next Day Percent Change": "2.91 %"
    },
    {
        "Hammer Date": "2014-10-02",
        "Next Day Percent Change": "0.74 %"
    },
    {
        "Hammer Date": "2015-11-20",
        "Next Day Percent Change": "1.12 %"
    },
    {
        "Hammer Date": "2016-03-21",
        "Next Day Percent Change": "2.82 %"
    },
    {
        "Hammer Date": "2016-04-22",
        "Next Day Percent Change": "1.56 %"
    },
    {
        "Hammer Date": "2017-02-06",
        "Next Day Percent Change": "0.39 %"
    },
    {
        "Hammer Date": "2017-08-04",
        "Next Day Percent Change": "0.16 %"
    },
    {
        "Hammer Date": "2018-02-09",
        "Next Day Percent Change": "1.58 %"
    },
    {
        "Hammer Date": "2018-03-19",
        "Next Day Percent Change": "2.33 %"
    },
    {
        "Hammer Date": "2018-03-28",
        "Next Day Percent Change": "2.94 %"
    },
    {
        "Hammer Date": "2018-04-16",
        "Next Day Percent Change": "2.84 %"
    },
    {
        "Hammer Date": "2018-07-05",
        "Next Day Percent Change": "0.86 %"
    },
    {
        "Hammer Date": "2019-04-15",
        "Next Day Percent Change": "0.63 %"
    },
    {
        "Hammer Date": "2019-08-06",
        "Next Day Percent Change": "1.09 %"
    },
    {
        "Hammer Date": "2019-10-03",
        "Next Day Percent Change": "0.79 %"
    },
    {
        "Hammer Date": "2020-06-29",
        "Next Day Percent Change": "2.75 %"
    },
    {
        "Hammer Date": "2020-10-22",
        "Next Day Percent Change": "0.42 %"
    },
    {
        "Hammer Date": "2020-10-23",
        "Next Day Percent Change": "0.26 %"
    },
    {
        "Hammer Date": "2021-03-26",
        "Next Day Percent Change": "0.66 %"
    },
    {
        "Hammer Date": "2022-01-10",
        "Next Day Percent Change": "2.39 %"
    },
    {
        "Hammer Date": "2022-09-16",
        "Next Day Percent Change": "2.05 %"
    },
    {
        "Hammer Date": "2022-11-22",
        "Next Day Percent Change": "0.95 %"
    },
    {
        "Hammer Date": "2023-03-20",
        "Next Day Percent Change": "2.52 %"
    },
    {
        "Hammer Date": "2024-06-03",
        "Next Day Percent Change": "0.96 %"
    }
]